LICENSE
MANIFEST.in
README.rst
setup.py
Gnotty.egg-info/PKG-INFO
Gnotty.egg-info/SOURCES.txt
Gnotty.egg-info/dependency_links.txt
Gnotty.egg-info/entry_points.txt
Gnotty.egg-info/not-zip-safe
Gnotty.egg-info/requires.txt
Gnotty.egg-info/top_level.txt
docs/conf.py
docs/index.rst
gnotty/__init__.py
gnotty/admin.py
gnotty/client.py
gnotty/conf.py
gnotty/models.py
gnotty/server.py
gnotty/urls.py
gnotty/views.py
gnotty/bots/__init__.py
gnotty/bots/base.py
gnotty/bots/chat.py
gnotty/bots/commands.py
gnotty/bots/commits.py
gnotty/bots/events.py
gnotty/bots/rss.py
gnotty/example_project/__init__.py
gnotty/example_project/manage.py
gnotty/example_project/settings.py
gnotty/example_project/urls.py
gnotty/management/__init__.py
gnotty/management/commands/__init__.py
gnotty/management/commands/gnottify.py
gnotty/management/commands/gnottify_runserver.py
gnotty/migrations/0001_initial.py
gnotty/migrations/0002_auto__add_field_ircmessage_join_or_leave.py
gnotty/migrations/0003_joins_leaves.py
gnotty/migrations/__init__.py
gnotty/static/css/bootstrap.responsive.css
gnotty/static/css/bootstrap.spacelab.css
gnotty/static/css/gnotty.css
gnotty/static/js/bootstrap.min.js
gnotty/static/js/gnotty.js
gnotty/static/js/jquery.min.js
gnotty/static/js/jquery.tmpl.min.js
gnotty/static/js/json2.js
gnotty/static/js/show-joins-leaves.js
gnotty/static/js/socket.io.min.js
gnotty/static/js/urlize.js
gnotty/static/swf/WebSocketMain.swf
gnotty/templates/gnotty/base.html
gnotty/templates/gnotty/calendar.html
gnotty/templates/gnotty/chat.html
gnotty/templates/gnotty/login.html
gnotty/templates/gnotty/messages.html
gnotty/templates/gnotty/test.html
gnotty/templates/gnotty/includes/nav.html
gnotty/templatetags/__init__.py
gnotty/templatetags/gnotty_tags.py